{"index.md":"32ee36b1","pinia_index.md":"13624210","project_consult-order.md":"c889daf4","project_consult.md":"d965f151","project_doctor.md":"4f584d15","project_end.md":"d97e32d4","project_home.md":"fc0b22b4","project_index.md":"45ca8f34","project_login.md":"7076dc3e","project_medicine.md":"69830000","project_order.md":"66b60f4a","project_room.md":"30f3fd47","project_super-doctor.md":"bb74eb33","project_user.md":"67e51baf","ts_backup.md":"904584fc","ts_case.md":"1c6a1117","ts_core.md":"54f8ed61","ts_index.md":"815f28ec","ts_pro.md":"d77151ac","vue_case.md":"a083facb","vue_composition.md":"227f0de0","vue_index.md":"f2bb6b5f"}
